README.rst
enigma.py
pyenigma.py
setup.py
crypto_enigma/__init__.py
crypto_enigma/_version.py
crypto_enigma/components.py
crypto_enigma/cypher.py
crypto_enigma/exceptions.py
crypto_enigma/machine.py
crypto_enigma/utils.py
crypto_enigma.egg-info/PKG-INFO
crypto_enigma.egg-info/SOURCES.txt
crypto_enigma.egg-info/dependency_links.txt
crypto_enigma.egg-info/top_level.txt